{
  "Routes": [

    // Catalog Microservice Route
    {
      "UpstreamHttpMethod": [ "Get", "Post", "Put", "Delete" ],
      "UpstreamPathTemplate": "/services/catalog/{everything}",
      "UpstreamScheme": "http",
      "AuthenticationOptions": {
        "AuthenticationProviderKey": "OcelotAuthenticationScheme",
        "AllowedScopes": [ "CatalogReadPermission" ]
      },
      "DownstreamPathTemplate": "/api/{everything}",
      "DownstreamScheme": "http",
      "DownstreamHostAndPorts": [
        {
          "Host": "localhost",
          "Port": 7252
        }
      ]
    },

    // Discount Microservice Route
    {
      "UpstreamHttpMethod": [ "Get", "Post", "Put", "Delete" ],
      "UpstreamPathTemplate": "/services/discount/{everything}",
      "UpstreamScheme": "http",
      "AuthenticationOptions": {
        "AuthenticationProviderKey": "OcelotAuthenticationScheme",
        "AllowedScopes": [ "DiscountFullPermission" ]
      },
      "DownstreamPathTemplate": "/api/{everything}",
      "DownstreamScheme": "http",
      "DownstreamHostAndPorts": [
        {
          "Host": "localhost",
          "Port": 7107
        }
      ]
    },    

    // Order Microservice Route
    {
      "UpstreamHttpMethod": [ "Get", "Post", "Put", "Delete" ],
      "UpstreamPathTemplate": "/services/order/{everything}",
      "UpstreamScheme": "http",
      "AuthenticationOptions": {
        "AuthenticationProviderKey": "OcelotAuthenticationScheme",
        "AllowedScopes": [ "OrderFullPermission" ]
      },
      "DownstreamPathTemplate": "/api/{everything}",
      "DownstreamScheme": "http",
      "DownstreamHostAndPorts": [
        {
          "Host": "localhost",
          "Port": 7165
        }
      ]
    },

    // Cargo Microservice Route
    {
      "UpstreamHttpMethod": [ "Get", "Post", "Put", "Delete" ],
      "UpstreamPathTemplate": "/services/cargo/{everything}",
      "UpstreamScheme": "http",
      "AuthenticationOptions": {
        "AuthenticationProviderKey": "OcelotAuthenticationScheme",
        "AllowedScopes": [ "CargoFullPermission" ]
      },
      "DownstreamPathTemplate": "/api/{everything}",
      "DownstreamScheme": "http",
      "DownstreamHostAndPorts": [
        {
          "Host": "localhost",
          "Port": 7088
        }
      ]
    },

    // Basket Microservice Route
    {
      "UpstreamHttpMethod": [ "Get", "Post", "Put", "Delete" ],
      "UpstreamPathTemplate": "/services/basket/{everything}",
      "UpstreamScheme": "http",
      "AuthenticationOptions": {
        "AuthenticationProviderKey": "OcelotAuthenticationScheme",
        "AllowedScopes": [ "BasketFullPermission" ]
      },
      "DownstreamPathTemplate": "/api/{everything}",
      "DownstreamScheme": "http",
      "DownstreamHostAndPorts": [
        {
          "Host": "localhost",
          "Port": 7019
        }
      ]
    },

    // Comment Microservice Route
    {
      "UpstreamHttpMethod": [ "Get", "Post", "Put", "Delete" ],
      "UpstreamPathTemplate": "/services/comment/{everything}",
      "UpstreamScheme": "http",
      "AuthenticationOptions": {
        "AuthenticationProviderKey": "OcelotAuthenticationScheme",
        "AllowedScopes": [ "CommentFullPermission" ]
      },
      "DownstreamPathTemplate": "/api/{everything}",
      "DownstreamScheme": "http",
      "DownstreamHostAndPorts": [
        {
          "Host": "localhost",
          "Port": 7047
        }
      ]
    },

    // Payment Microservice Route
    {
      "UpstreamHttpMethod": [ "Get", "Post", "Put", "Delete" ],
      "UpstreamPathTemplate": "/services/payment/{everything}",
      "UpstreamScheme": "http",
      "AuthenticationOptions": {
        "AuthenticationProviderKey": "OcelotAuthenticationScheme",
        "AllowedScopes": [ "PaymentFullPermission" ]
      },
      "DownstreamPathTemplate": "/api/{everything}",
      "DownstreamScheme": "http",
      "DownstreamHostAndPorts": [
        {
          "Host": "localhost",
          "Port": 7218
        }
      ]
    },

    // Images Microservice Route
    {
      "UpstreamHttpMethod": [ "Get", "Post", "Put", "Delete" ],
      "UpstreamPathTemplate": "/services/images/{everything}",
      "UpstreamScheme": "http",
      "AuthenticationOptions": {
        "AuthenticationProviderKey": "OcelotAuthenticationScheme",
        "AllowedScopes": [ "ImagesFullPermission" ]
      },
      "DownstreamPathTemplate": "/api/{everything}",
      "DownstreamScheme": "http",
      "DownstreamHostAndPorts": [
        {
          "Host": "localhost",
          "Port": 7153
        }
      ]
    },

    // Message Microservice Route
    {
      "UpstreamHttpMethod": [ "Get", "Post", "Put", "Delete" ],
      "UpstreamPathTemplate": "/services/message/{everything}",
      "UpstreamScheme": "http",
      "AuthenticationOptions": {
        "AuthenticationProviderKey": "OcelotAuthenticationScheme",
        "AllowedScopes": [ "MessageFullPermission" ]
      },
      "DownstreamPathTemplate": "/api/{everything}",
      "DownstreamScheme": "http",
      "DownstreamHostAndPorts": [
        {
          "Host": "localhost",
          "Port": 7257
        }
      ]
    }
  ],
  "GlobalConfiguration": {
    "BaseUrl": "http://localhost:5104"
  }
}
